MANIFEST.in
README.rst
setup.cfg
setup.py
versioneer.py
scikit_surgeryfred.egg-info/PKG-INFO
scikit_surgeryfred.egg-info/SOURCES.txt
scikit_surgeryfred.egg-info/dependency_links.txt
scikit_surgeryfred.egg-info/requires.txt
scikit_surgeryfred.egg-info/top_level.txt
sksurgeryfred/__init__.py
sksurgeryfred/_version.py
sksurgeryfred/algorithms/__init__.py
sksurgeryfred/algorithms/errors.py
sksurgeryfred/algorithms/fle.py
sksurgeryfred/algorithms/fred.py
sksurgeryfred/algorithms/point_based_reg.py
sksurgeryfred/algorithms/scores.py
sksurgeryfred/utilities/__init__.py
sksurgeryfred/utilities/get_results.py
sksurgeryfred/utilities/results_database.py
tests/algorithms/__init__.py
tests/algorithms/test_errors.py
tests/algorithms/test_fle.py
tests/algorithms/test_pbr.py
tests/algorithms/test_scores.py
tests/utilities/__init__.py
tests/utilities/test_get_results.py